mdbt/__init__.py
mdbt/ai_core.py
mdbt/build_dbt_docs_ai.py
mdbt/build_unit_test_data_ai.py
mdbt/cmdline.py
mdbt/core.py
mdbt/expectations_output_builder.py
mdbt/lightdash.py
mdbt/main.py
mdbt/precommit_format.py
mdbt/prompts.py
mdbt/recce.py
mdbt/sort_yaml_fields.py
mdbt/sql_sorter.py
mdbt-0.4.34.dist-info/licenses/LICENSE
mdbt-0.4.34.dist-info/METADATA
mdbt-0.4.34.dist-info/WHEEL
mdbt-0.4.34.dist-info/entry_points.txt
mdbt-0.4.34.dist-info/top_level.txt
mdbt-0.4.34.dist-info/RECORD
