Metadata-Version: 2.4
Name: mdbt
Version: 0.4.34
Summary: A CLI tool to manage dbt builds with state handling and manifest management
Author: Craig Lathrop
Author-email: info@markimicrowave.com
Classifier: Programming Language :: Python :: 3
Classifier: License :: OSI Approved :: MIT License
Classifier: Operating System :: OS Independent
Requires-Python: >=3.9
License-File: LICENSE
Requires-Dist: click<9.0.0,>=8.0.0
Requires-Dist: pyperclip<2.0.0,>=1.8.0
Requires-Dist: snowflake-connector-python[pandas]<4.0.0,>=3.11.0
Requires-Dist: python-dotenv<1.2.0,>=1.0.0
Requires-Dist: openai<2.0.0,>=1.35.0
Requires-Dist: sqlfluff==3.4.0
Requires-Dist: sqlfluff-templater-dbt==3.4.0
Requires-Dist: wordninja==2.0.0
Requires-Dist: ruamel.yaml<0.18.0
Requires-Dist: recce<=0.44.3
Dynamic: author
Dynamic: author-email
Dynamic: classifier
Dynamic: license-file
Dynamic: requires-dist
Dynamic: requires-python
Dynamic: summary
